zeroml/__init__.py
zeroml/cli.py
zeroml/dataloading/__init__.py
zeroml/dataloading/image/__init__.py
zeroml/dataloading/image/datasets.py
zeroml/dataloading/image/transforms.py
zeroml/dl/__init__.py
zeroml/dl/losses.py
zeroml/dl/models.py
zeroml/io/__init__.py
zeroml/io/image.py
zeroml/io/neptuneai.py
zeroml/plutils/__init__.py
zeroml/visualize/__init__.py
zeroml-0.4.0.dist-info/entry_points.txt
zeroml-0.4.0.dist-info/LICENSE
zeroml-0.4.0.dist-info/WHEEL
zeroml-0.4.0.dist-info/METADATA
zeroml-0.4.0.dist-info/RECORD
